baybars/__init__.py
baybars/azure_blob.py
baybars/azure_queue.py
baybars/azure_table.py
baybars/constants.py
baybars/consul_values.py
baybars/data_types.py
baybars/docdb.py
baybars/era.py
baybars/ftp.py
baybars/gz.py
baybars/image_processor.py
baybars/kafka_consumer.py
baybars/kafka_producer.py
baybars/moment.py
baybars/nomad.py
baybars/presto.py
baybars/requirements.txt
baybars/setup.cfg
baybars/tar.py
baybars/timber.py
baybars/vault.py
baybars/elastic/__init__.py
baybars/elastic/data_types.py
baybars/elastic/query.py
baybars/ml_models/__init__.py
baybars/ml_models/word2vec.py
baybars/ml_models/vectorizer/__init__.py
baybars/ml_models/vectorizer/mean_weighted_vectorizer.py
baybars/ml_models/vectorizer/tfidf_weighted_vectorizer.py
baybars/tf_models/__init__.py
baybars/tf_models/cnn/.gitignore
baybars/tf_models/cnn/text_classifier.py
baybars/tf_models/embedding/__init__.py
baybars/tf_models/embedding/word_simple_model.py
baybars/tf_models/seq2seq/__init__.py
baybars/tf_models/seq2seq/bahdanau_attention.py
baybars-0.0.26.dist-info/AUTHORS
baybars-0.0.26.dist-info/LICENSE
baybars-0.0.26.dist-info/METADATA
baybars-0.0.26.dist-info/WHEEL
baybars-0.0.26.dist-info/pbr.json
baybars-0.0.26.dist-info/top_level.txt
baybars-0.0.26.dist-info/RECORD
