Metadata-Version: 2.1
Name: baybars
Version: 0.0.26
Summary: Python Common Packages that we use at Jet
Home-page: https://github.com/jet/baybars
Author: Bugra Akyildiz
Author-email: bugra.akyildiz@jet.com
License: UNKNOWN
Keywords: azure kafka blob documentdb cosmosdb queue tar
Platform: UNKNOWN
Classifier: Development Status :: 3 - Alpha
Classifier: Programming Language :: Python :: 3.5
Classifier: Programming Language :: Python :: 3.6
Classifier: Intended Audience :: Developers
Requires-Python: >=3.5
